RNAtweaks/RNAtweaks.py
RNAtweaks/__init__.py
RNAtweaks-0.0.2.dist-info/LICENSE.txt
RNAtweaks-0.0.2.dist-info/METADATA
RNAtweaks-0.0.2.dist-info/WHEEL
RNAtweaks-0.0.2.dist-info/top_level.txt
RNAtweaks-0.0.2.dist-info/RECORD
