Metadata-Version: 2.1
Name: RNAtweaks
Version: 0.0.2
Summary: Package including ViennaRNA helper functions and classes
Home-page: https://github.com/domonik/RNAtweaks
Author: Dominik Rabsch
Author-email: rabsch@informatik.uni-freiburg.de
License: LICENSE.txt
Platform: UNKNOWN
Requires-Dist: numpy
